cnpj_val/__init__.py
cnpj_val/cnpj_val.py
cnpj_val/cnpj_validator.py
cnpj_val-1.0.2.dist-info/licenses/LICENSE
cnpj_val-1.0.2.dist-info/METADATA
cnpj_val-1.0.2.dist-info/WHEEL
cnpj_val-1.0.2.dist-info/top_level.txt
cnpj_val-1.0.2.dist-info/RECORD
